{
    "pedal": 246,
    "path": "/datasets/dataset1/Rider1/734.gpx",
    "creator": "StravaGPX",
    "coordinateInicial": "46.0777920|14.8257480",
    "coordinateFinal": "46.0773790|14.8255450",
    "country": "Slovenia",
    "locality": "Litija",
    "centroid": "46.048952500000006|14.78788",
    "bbox": "[[46.020113,14.729904],[46.077792,14.729904],[46.077792,14.845856],[46.020113,14.845856],[46.020113,14.729904]]",
    "datetime": "2013-06-23 05:50:38",
    "duration": "1:39:32",
    "distance": "40.42",
    "elevation_gps": "337.6030",
    "elevation_google": "337.0340",
    "elevation_bing": "339.6454",
    "speed_avg": "24.37",
    "heartrate_avg": "134.53",
    "temperature_avg": "23.1294",
    "trackpoints": "5471"
}