{
    "pedal": 318,
    "path": "/datasets/dataset2/Rider1/404.gpx",
    "creator": "Garmin Connect",
    "coordinateInicial": "46.454343097284436|15.337453186511993",
    "coordinateFinal": "46.453078435733914|15.333556523546576",
    "country": "Slovenia",
    "locality": "Zre\u010de",
    "centroid": "46.43825535|15.347128649999998",
    "bbox": "[[46.4209064,15.3207534],[46.4556043,15.3207534],[46.4556043,15.3735039],[46.4209064,15.3735039],[46.4209064,15.3207534]]",
    "datetime": "2014-07-11 08:49:00",
    "duration": "1:5:1",
    "distance": "18.18",
    "elevation_gps": "1016.2273",
    "elevation_google": "1233.4090",
    "elevation_bing": "1240.7327",
    "speed_avg": "16.78",
    "heartrate_avg": "116.72",
    "temperature_avg": "14.9146",
    "trackpoints": "3887"
}