{
    "pedal": 272,
    "path": "/datasets/dataset3/Rider3/299.gpx",
    "creator": "Garmin Connect",
    "coordinateInicial": "46.53829908929765|16.17399956099689",
    "coordinateFinal": "46.53845834545791|16.17540931329131",
    "country": "Slovenia",
    "locality": "Ljutomer",
    "centroid": "46.59088885|16.1458148",
    "bbox": "[[46.5271743,16.0161551],[46.6546034,16.0161551],[46.6546034,16.2754745],[46.5271743,16.2754745],[46.5271743,16.0161551]]",
    "datetime": "2014-06-11 13:51:09",
    "duration": "3:51:13",
    "distance": "79.20",
    "elevation_gps": "200.5897",
    "elevation_google": "206.3769",
    "elevation_bing": "207.5059",
    "speed_avg": "20.55",
    "heartrate_avg": "129.31",
    "temperature_avg": "35.0819",
    "trackpoints": "3467"
}