{
    "pedal": 109,
    "path": "/datasets/dataset2/Rider3/155.gpx",
    "creator": "StravaGPX",
    "coordinateInicial": "46.0784810|14.5165300",
    "coordinateFinal": "46.0782050|14.5166650",
    "country": "Slovenia",
    "locality": "Ljubljana",
    "centroid": "46.110971|14.5053765",
    "bbox": "[[46.078044,14.490398],[46.143898,14.490398],[46.143898,14.520355],[46.078044,14.520355],[46.078044,14.490398]]",
    "datetime": "2015-02-26 14:58:33",
    "duration": "1:32:35",
    "distance": "21.50",
    "elevation_gps": "309.0721",
    "elevation_google": "375.2971",
    "elevation_bing": "382.6740",
    "speed_avg": "13.93",
    "heartrate_avg": "133.57",
    "temperature_avg": "7.0032",
    "trackpoints": "2485"
}