{
    "pedal": 109,
    "path": "/datasets/dataset1/Rider2/139.gpx",
    "creator": "StravaGPX",
    "coordinateInicial": "46.5172940|16.2036800",
    "coordinateFinal": "46.5172880|16.2034990",
    "country": "Slovenia",
    "locality": "Ljutomer",
    "centroid": "46.479479|16.227995",
    "bbox": "[[46.441184,16.201058],[46.517774,16.201058],[46.517774,16.254932],[46.441184,16.254932],[46.441184,16.201058]]",
    "datetime": "2014-03-22 13:08:30",
    "duration": "1:54:54",
    "distance": "33.93",
    "elevation_gps": "269.0561",
    "elevation_google": "253.7518",
    "elevation_bing": "255.1837",
    "speed_avg": "17.72",
    "heartrate_avg": "123.72",
    "temperature_avg": "16.7707",
    "trackpoints": "3403"
}