{
    "pedal": 107,
    "path": "/datasets/dataset2/Rider2/381.gpx",
    "creator": "StravaGPX",
    "coordinateInicial": "46.0667460|14.5040970",
    "coordinateFinal": "46.0673150|14.5201840",
    "country": "Slovenia",
    "locality": "Ljubljana",
    "centroid": "46.076428500000006|14.4689665",
    "bbox": "[[46.065795,14.417621],[46.087062,14.417621],[46.087062,14.520312],[46.065795,14.520312],[46.065795,14.417621]]",
    "datetime": "2015-08-26 12:33:45",
    "duration": "1:29:55",
    "distance": "27.17",
    "elevation_gps": "334.6562",
    "elevation_google": "397.0805",
    "elevation_bing": "402.0448",
    "speed_avg": "18.13",
    "heartrate_avg": "130.17",
    "temperature_avg": "24.4808",
    "trackpoints": "3434"
}