{
    "pedal": 123,
    "path": "/datasets/dataset1/Rider7/126.gpx",
    "creator": "StravaGPX",
    "coordinateInicial": "46.5437010|14.9485810",
    "coordinateFinal": "46.5415770|14.9454230",
    "country": "Slovenia",
    "locality": "Ravne na Koro\u0161kem",
    "centroid": "46.5490545|14.932492500000002",
    "bbox": "[[46.539112,14.916404],[46.558997,14.916404],[46.558997,14.948581],[46.539112,14.948581],[46.539112,14.916404]]",
    "datetime": "2014-04-02 14:09:01",
    "duration": "1:43:5",
    "distance": "15.15",
    "elevation_gps": "532.9976",
    "elevation_google": "496.0130",
    "elevation_bing": "497.9497",
    "speed_avg": "8.82",
    "heartrate_avg": "106.15",
    "temperature_avg": "21.2880",
    "trackpoints": "2226"
}