{
    "pedal": 260,
    "path": "/datasets/dataset3/Rider13/306.gpx",
    "creator": "Garmin Connect",
    "coordinateInicial": "-29.570612423121929168701171875|30.35243620164692401885986328125",
    "coordinateFinal": "-29.5916654169559478759765625|30.37040054798126220703125",
    "country": "South Africa",
    "locality": "Pietermaritzburg",
    "centroid": "-29.579266500000003|30.36121025",
    "bbox": "[[-29.591665,30.3481362],[-29.566868,30.3481362],[-29.566868,30.3742843],[-29.591665,30.3742843],[-29.591665,30.3481362]]",
    "datetime": "2014-04-11 08:27:30",
    "duration": "1:20:11",
    "distance": "9.49",
    "elevation_gps": "734.8979",
    "elevation_google": "723.3841",
    "elevation_bing": "730.7489",
    "speed_avg": "7.10",
    "heartrate_avg": "130.54",
    "temperature_avg": "29.9763",
    "trackpoints": "2612"
}