{
    "pedal": 293,
    "path": "/datasets/dataset1/Rider7/319.gpx",
    "creator": "StravaGPX",
    "coordinateInicial": "46.5501750|14.9398280",
    "coordinateFinal": "46.5416350|14.9453730",
    "country": "Slovenia",
    "locality": "Prevalje",
    "centroid": "46.5491685|14.884491",
    "bbox": "[[46.493812,14.822397],[46.604525,14.822397],[46.604525,14.946585],[46.493812,14.946585],[46.493812,14.822397]]",
    "datetime": "2014-07-17 08:12:57",
    "duration": "5:17:20",
    "distance": "64.33",
    "elevation_gps": "850.2402",
    "elevation_google": "761.8457",
    "elevation_bing": "769.2798",
    "speed_avg": "12.16",
    "heartrate_avg": "121.43",
    "temperature_avg": "23.1935",
    "trackpoints": "9662"
}