{
    "pedal": 332,
    "path": "/datasets/dataset2/Rider1/425.gpx",
    "creator": "Garmin Connect",
    "coordinateInicial": "44.967586090788245|14.749237541109324",
    "coordinateFinal": "44.96764342300594|14.749369388446212",
    "country": "Croatia",
    "locality": "Ba\u0161ka",
    "centroid": "45.033316850000006|14.6850865",
    "bbox": "[[44.9633352,14.605598],[45.1032985,14.605598],[45.1032985,14.764575],[44.9633352,14.764575],[44.9633352,14.605598]]",
    "datetime": "2015-04-15 08:00:03",
    "duration": "3:40:13",
    "distance": "68.83",
    "elevation_gps": "181.3338",
    "elevation_google": "181.6550",
    "elevation_bing": "182.4002",
    "speed_avg": "18.75",
    "heartrate_avg": "141.77",
    "temperature_avg": "26.4569",
    "trackpoints": "13160"
}