{
    "pedal": 505,
    "path": "/datasets/dataset3/Rider12/712.gpx",
    "creator": "StravaGPX",
    "coordinateInicial": "46.0621160|14.8161120",
    "coordinateFinal": "46.0621890|14.8161280",
    "country": "Slovenia",
    "locality": "Litija",
    "centroid": "46.0596065|14.739419499999999",
    "bbox": "[[46.0122,14.633087],[46.107013,14.633087],[46.107013,14.845752],[46.0122,14.845752],[46.0122,14.633087]]",
    "datetime": "2016-09-04 09:23:10",
    "duration": "3:23:12",
    "distance": "55.31",
    "elevation_gps": "335.2058",
    "elevation_google": "335.3859",
    "elevation_bing": "338.7622",
    "speed_avg": "16.33",
    "heartrate_avg": "108.81",
    "temperature_avg": "26.3818",
    "trackpoints": "2902"
}