{
    "pedal": 1,
    "path": "/datasets/dataset2/Rider2/1.gpx",
    "creator": "StravaGPX",
    "coordinateInicial": "46.0780540|14.5197770",
    "coordinateFinal": "46.0681150|14.5177430",
    "country": "Slovenia",
    "locality": "Ljubljana",
    "centroid": "46.104974|14.510024999999999",
    "bbox": "[[46.068109,14.499848],[46.141839,14.499848],[46.141839,14.520202],[46.068109,14.520202],[46.068109,14.499848]]",
    "datetime": "2014-02-26 14:31:54",
    "duration": "1:31:51",
    "distance": "27.58",
    "elevation_gps": "362.0362",
    "elevation_google": "404.6575",
    "elevation_bing": "411.1096",
    "speed_avg": "18.02",
    "heartrate_avg": "127.13",
    "temperature_avg": "13.0927",
    "trackpoints": "3366"
}