{
    "pedal": 260,
    "path": "/datasets/dataset1/Rider7/273.gpx",
    "creator": "StravaGPX",
    "coordinateInicial": "46.5415390|14.9453660",
    "coordinateFinal": "46.5416310|14.9454480",
    "country": "Slovenia",
    "locality": "Ravne na Koro\u0161kem",
    "centroid": "46.52744150000001|14.9428005",
    "bbox": "[[46.512737,14.924355],[46.542146,14.924355],[46.542146,14.961246],[46.512737,14.961246],[46.512737,14.924355]]",
    "datetime": "2013-06-09 08:19:14",
    "duration": "2:16:33",
    "distance": "26.39",
    "elevation_gps": "549.9667",
    "elevation_google": "531.9737",
    "elevation_bing": "543.4779",
    "speed_avg": "11.60",
    "heartrate_avg": "124.51",
    "temperature_avg": "23.2938",
    "trackpoints": "4714"
}