{
    "pedal": 18,
    "path": "/datasets/dataset2/Rider3/24.gpx",
    "creator": "StravaGPX",
    "coordinateInicial": "46.0781980|14.5166840",
    "coordinateFinal": "46.0779600|14.5161070",
    "country": "Slovenia",
    "locality": "Ljubljana",
    "centroid": "46.10037|14.522446000000002",
    "bbox": "[[46.07796,14.507452],[46.12278,14.507452],[46.12278,14.53744],[46.07796,14.53744],[46.07796,14.507452]]",
    "datetime": "2015-09-03 14:36:52",
    "duration": "1:3:52",
    "distance": "20.46",
    "elevation_gps": "311.7554",
    "elevation_google": "327.2375",
    "elevation_bing": "333.1922",
    "speed_avg": "19.22",
    "heartrate_avg": "116.40",
    "temperature_avg": "19.3500",
    "trackpoints": "1582"
}