{
    "pedal": 58,
    "path": "/datasets/dataset1/Rider1/161.gpx",
    "creator": "StravaGPX",
    "coordinateInicial": "44.2860480|11.8836690",
    "coordinateFinal": "44.2859560|11.8836800",
    "country": "Italy",
    "locality": "Faenza",
    "centroid": "44.1629175|11.798067999999999",
    "bbox": "[[44.023283,11.707084],[44.302552,11.707084],[44.302552,11.889052],[44.023283,11.889052],[44.023283,11.707084]]",
    "datetime": "2014-03-16 08:31:13",
    "duration": "3:19:59",
    "distance": "115.75",
    "elevation_gps": "275.2543",
    "elevation_google": "287.1155",
    "elevation_bing": "287.6323",
    "speed_avg": "34.73",
    "heartrate_avg": "160.16",
    "temperature_avg": "18.7784",
    "trackpoints": "11991"
}