{
    "pedal": 116,
    "path": "/datasets/dataset1/Rider1/292.gpx",
    "creator": "StravaGPX",
    "coordinateInicial": "46.2256820|14.6116090",
    "coordinateFinal": "46.2307810|14.6103560",
    "country": "Slovenia",
    "locality": "Kamnik",
    "centroid": "46.311222|14.639876000000001",
    "bbox": "[[46.194805,14.424161],[46.427639,14.424161],[46.427639,14.855591],[46.194805,14.855591],[46.194805,14.424161]]",
    "datetime": "2014-09-30 06:56:40",
    "duration": "6:13:28",
    "distance": "137.59",
    "elevation_gps": "702.7325",
    "elevation_google": "698.4789",
    "elevation_bing": "704.3969",
    "speed_avg": "22.10",
    "heartrate_avg": "155.64",
    "temperature_avg": "19.5878",
    "trackpoints": "19127"
}