{
    "pedal": 222,
    "path": "/datasets/dataset2/Rider5/233.gpx",
    "creator": "StravaGPX",
    "coordinateInicial": "46.5420310|14.9456330",
    "coordinateFinal": "46.5416740|14.9453890",
    "country": "Slovenia",
    "locality": "Ravne na Koro\u0161kem",
    "centroid": "46.5617445|14.953031000000001",
    "bbox": "[[46.541674,14.929675],[46.581815,14.929675],[46.581815,14.976387],[46.541674,14.976387],[46.541674,14.929675]]",
    "datetime": "2015-03-20 09:18:52",
    "duration": "2:21:44",
    "distance": "25.47",
    "elevation_gps": "518.3268",
    "elevation_google": "607.1707",
    "elevation_bing": "612.0558",
    "speed_avg": "10.78",
    "heartrate_avg": "102.58",
    "temperature_avg": "10.0465",
    "trackpoints": "4298"
}