{
    "pedal": 395,
    "path": "/datasets/dataset1/Rider4/800.gpx",
    "creator": "StravaGPX",
    "coordinateInicial": "46.5537320|15.6444970",
    "coordinateFinal": "46.5580010|15.6476560",
    "country": "Slovenia",
    "locality": "Maribor",
    "centroid": "46.4840585|15.582481000000001",
    "bbox": "[[46.410116,15.507419],[46.558001,15.507419],[46.558001,15.657543],[46.410116,15.657543],[46.410116,15.507419]]",
    "datetime": "2014-07-03 09:08:35",
    "duration": "3:46:11",
    "distance": "84.61",
    "elevation_gps": "476.5085",
    "elevation_google": "581.3405",
    "elevation_bing": "582.0893",
    "speed_avg": "22.44",
    "heartrate_avg": "132.29",
    "temperature_avg": "26.2417",
    "trackpoints": "6851"
}