{
    "pedal": 130,
    "path": "/datasets/dataset3/Rider14/421.gpx",
    "creator": "StravaGPX",
    "coordinateInicial": "46.0644440|14.5426930",
    "coordinateFinal": "46.0664500|14.5247630",
    "country": "Slovenia",
    "locality": "Ljubljana",
    "centroid": "46.0468755|14.537831500000001",
    "bbox": "[[46.026513,14.516712],[46.067238,14.516712],[46.067238,14.558951],[46.026513,14.558951],[46.026513,14.516712]]",
    "datetime": "2015-06-14 07:17:41",
    "duration": "1:23:44",
    "distance": "21.83",
    "elevation_gps": "344.2935",
    "elevation_google": "375.5008",
    "elevation_bing": "384.6503",
    "speed_avg": "15.64",
    "heartrate_avg": "132.58",
    "temperature_avg": "24.0646",
    "trackpoints": "2725"
}