{
    "pedal": 370,
    "path": "/datasets/dataset2/Rider1/436.gpx",
    "creator": "Garmin Connect",
    "coordinateInicial": "-16.747090565040708|145.6696071010083",
    "coordinateFinal": "-16.747276224195957|145.66965035162866",
    "country": "Australia",
    "locality": "Palm Cove",
    "centroid": "-16.784368|145.677795",
    "bbox": "[[-16.821646,145.661932],[-16.74709,145.661932],[-16.74709,145.693658],[-16.821646,145.693658],[-16.821646,145.661932]]",
    "datetime": "2014-04-20 00:12:01",
    "duration": "3:29:55",
    "distance": "42.63",
    "elevation_gps": "51.9194",
    "elevation_google": "47.7863",
    "elevation_bing": "57.0265",
    "speed_avg": "12.18",
    "heartrate_avg": "146.62",
    "temperature_avg": "29.1848",
    "trackpoints": "4193"
}