{
    "pedal": 508,
    "path": "/datasets/dataset3/Rider3/554.gpx",
    "creator": "Garmin Connect",
    "coordinateInicial": "45.80438199453056|15.168399335816503",
    "coordinateFinal": "45.780764389783144|15.268701547756791",
    "country": "Slovenia",
    "locality": "Novo mesto",
    "centroid": "45.824835050000004|15.2348809",
    "bbox": "[[45.7807643,15.1643829],[45.8689058,15.1643829],[45.8689058,15.3053789],[45.7807643,15.3053789],[45.7807643,15.1643829]]",
    "datetime": "2016-04-03 12:41:53",
    "duration": "1:19:56",
    "distance": "29.24",
    "elevation_gps": "164.5148",
    "elevation_google": "193.9530",
    "elevation_bing": "195.8406",
    "speed_avg": "21.95",
    "heartrate_avg": "141.66",
    "temperature_avg": "20.6388",
    "trackpoints": "3845"
}