{
    "pedal": 123,
    "path": "/datasets/dataset3/Rider3/138.gpx",
    "creator": "Garmin Connect",
    "coordinateInicial": "46.53818232938647|16.174607248976827",
    "coordinateFinal": "46.53818710707128|16.17507018148899",
    "country": "Slovenia",
    "locality": "Ljutomer",
    "centroid": "46.53621185|16.0996736",
    "bbox": "[[46.5192723,16.0242771],[46.5531514,16.0242771],[46.5531514,16.1750701],[46.5192723,16.1750701],[46.5192723,16.0242771]]",
    "datetime": "2014-11-16 11:58:05",
    "duration": "2:19:46",
    "distance": "31.00",
    "elevation_gps": "229.8324",
    "elevation_google": "197.1805",
    "elevation_bing": "197.8260",
    "speed_avg": "13.31",
    "heartrate_avg": "123.45",
    "temperature_avg": "19.2137",
    "trackpoints": "1914"
}