{
    "pedal": 82,
    "path": "/datasets/dataset1/Rider1/212.gpx",
    "creator": "StravaGPX",
    "coordinateInicial": "46.0785860|14.8262320",
    "coordinateFinal": "45.9982950|14.5561330",
    "country": "Slovenia",
    "locality": "Litija",
    "centroid": "46.05257099999999|14.684822",
    "bbox": "[[45.998079,14.532354],[46.107063,14.532354],[46.107063,14.83729],[45.998079,14.83729],[45.998079,14.532354]]",
    "datetime": "2012-11-24 10:55:47",
    "duration": "3:49:7",
    "distance": "57.23",
    "elevation_gps": "334.6767",
    "elevation_google": "330.3246",
    "elevation_bing": "335.0244",
    "speed_avg": "14.99",
    "heartrate_avg": "121.05",
    "temperature_avg": "12.0390",
    "trackpoints": "11457"
}